sliceguard/__init__.py
sliceguard/data.py
sliceguard/detection.py
sliceguard/embeddings.py
sliceguard/explanation.py
sliceguard/modeling.py
sliceguard/sliceguard.py
sliceguard/utils.py
sliceguard/models/__init__.py
sliceguard/models/huggingface.py
sliceguard-0.0.35.dist-info/LICENSE
sliceguard-0.0.35.dist-info/METADATA
sliceguard-0.0.35.dist-info/WHEEL
sliceguard-0.0.35.dist-info/top_level.txt
sliceguard-0.0.35.dist-info/RECORD
